{"version":1,"resource":"file:///Users/amadeo.manouchehri/repos/personio-web/product-areas/payroll/views/preliminary-payroll/src/integrations/payroll-gb/components/PayrollRunTab/EmployeePensions/AllocationItem.tsx","entries":[{"id":"y1ys.tsx","timestamp":1721299701980},{"id":"c2Mm.tsx","source":"Fix all fixable ESLint issues","timestamp":1721300350875},{"id":"hWZo.tsx","source":"Fix all fixable ESLint issues","timestamp":1721305051147},{"id":"JwWB.tsx","source":"Fix all fixable ESLint issues","timestamp":1721307820663},{"id":"iGu0.tsx","timestamp":1721307822944},{"id":"tSZy.tsx","timestamp":1721309438959},{"id":"W84o.tsx","source":"Fix all fixable ESLint issues","timestamp":1721374801902},{"id":"xQ0v.tsx","timestamp":1721374853390},{"id":"gBZH.tsx","timestamp":1721376908294},{"id":"DqDd.tsx","source":"Fix all fixable ESLint issues","timestamp":1721399557389},{"id":"aMMM.tsx","timestamp":1721399583057},{"id":"oy9B.tsx","source":"Fix all fixable ESLint issues","timestamp":1721399593076},{"id":"9eY8.tsx","timestamp":1721399607107},{"id":"Hzwr.tsx","timestamp":1721399635724},{"id":"tw79.tsx","source":"Fix all fixable ESLint issues","timestamp":1721399690971},{"id":"GVAn.tsx","source":"Fix all fixable ESLint issues","timestamp":1721399715981},{"id":"7A3I.tsx","timestamp":1721399722567},{"id":"myQO.tsx","source":"Fix all fixable ESLint issues","timestamp":1721399740235},{"id":"IKsc.tsx","timestamp":1721399748198},{"id":"qDw2.tsx","source":"Fix all fixable ESLint issues","timestamp":1721399754271},{"id":"1a03.tsx","timestamp":1721399759783},{"id":"rHLi.tsx","source":"Fix all fixable ESLint issues","timestamp":1721399818451},{"id":"EFi8.tsx","source":"undoRedo.source","timestamp":1721399840532},{"id":"QrHq.tsx","timestamp":1721400007594},{"id":"YFwR.tsx","source":"Fix all fixable ESLint issues","timestamp":1721400042522},{"id":"If3I.tsx","source":"Fix all fixable ESLint issues","timestamp":1721400095253},{"id":"KXSL.tsx","timestamp":1721400101493},{"id":"Jsxl.tsx","timestamp":1721400133596},{"id":"MRte.tsx","source":"Fix all fixable ESLint issues","timestamp":1721400153951},{"id":"Kvq8.tsx","timestamp":1721400156170},{"id":"mkYj.tsx","source":"Fix all fixable ESLint issues","timestamp":1721400172569},{"id":"asb2.tsx","source":"Fix all fixable ESLint issues","timestamp":1721400211988},{"id":"ur4Q.tsx","source":"Fix all fixable ESLint issues","timestamp":1721400228185},{"id":"J5MK.tsx","timestamp":1721400230589},{"id":"uqbw.tsx","timestamp":1721400341964},{"id":"k03w.tsx","source":"Fix all fixable ESLint issues","timestamp":1721400439985},{"id":"5WCV.tsx","timestamp":1721400597575},{"id":"FSmg.tsx","source":"Fix all fixable ESLint issues","timestamp":1721400677161},{"id":"hHMC.tsx","source":"Fix all fixable ESLint issues","timestamp":1721404828128},{"id":"pSgg.tsx","timestamp":1721404851400},{"id":"CiqD.tsx","source":"Fix all fixable ESLint issues","timestamp":1721404937388},{"id":"JVHL.tsx","timestamp":1721404941861},{"id":"m9zO.tsx","timestamp":1721405091395},{"id":"qH23.tsx","source":"Fix all fixable ESLint issues","timestamp":1721405374408},{"id":"GaKh.tsx","source":"Fix all fixable ESLint issues","timestamp":1721405406846},{"id":"HJUJ.tsx","source":"Fix all fixable ESLint issues","timestamp":1721405422187},{"id":"mjh0.tsx","source":"Fix all fixable ESLint issues","timestamp":1721405486372},{"id":"M0Xq.tsx","timestamp":1721405511355},{"id":"Ef76.tsx","source":"undoRedo.source","timestamp":1721405611285},{"id":"m4Cy.tsx","source":"Fix all fixable ESLint issues","timestamp":1721406233957}]}