{"version":1,"resource":"file:///Users/amadeo.manouchehri/repos/personio-web/product-areas/employees-organizations/gofer/src/hooks/custom/useOrgUnitCardData.ts","entries":[{"id":"pA2d.ts","source":"Fix all fixable ESLint issues","timestamp":1760435259024},{"id":"Dwqm.ts","timestamp":1760435297381},{"id":"FoKq.ts","source":"undoRedo.source","timestamp":1760435367905},{"id":"LD5F.ts","source":"Fix all fixable ESLint issues","timestamp":1760445757665},{"id":"rUrI.ts","source":"Fix all fixable ESLint issues","timestamp":1760445772800},{"id":"tlc9.ts","source":"undoRedo.source","timestamp":1760445803145},{"id":"XbSk.ts","source":"Fix all fixable ESLint issues","timestamp":1760690637078},{"id":"zqIx.ts","source":"undoRedo.source","timestamp":1760690672025},{"id":"Xzra.ts","source":"Fix all fixable ESLint issues","timestamp":1762352943894},{"id":"pyBp.ts","source":"Fix all fixable ESLint issues","timestamp":1762352984263},{"id":"UT2k.ts","source":"Fix all fixable ESLint issues","timestamp":1762353599659},{"id":"bdVO.ts","source":"Fix all fixable ESLint issues","timestamp":1762353667337},{"id":"ADwa.ts","source":"Fix all fixable ESLint issues","timestamp":1762353728883},{"id":"vaRo.ts","timestamp":1762353731360},{"id":"46Cg.ts","timestamp":1763981584788},{"id":"IbU6.ts","timestamp":1763981635180},{"id":"VMYV.ts","timestamp":1764172557578},{"id":"awl8.ts","timestamp":1764172737495}]}