{"version":1,"resource":"file:///Users/amadeo.manouchehri/repos/personio-web/product-areas/payroll/views/preliminary-payroll/src/integrations/payroll-gb/tabs/PayRunsTab/tableUtils/filters.test.ts","entries":[{"id":"ZamZ.ts","source":"Fix all fixable ESLint issues","timestamp":1727452233651},{"id":"KaMi.ts","timestamp":1727452252432},{"id":"qGIi.ts","timestamp":1727452290494},{"id":"1oH3.ts","source":"Fix all fixable ESLint issues","timestamp":1727452311196},{"id":"63Hc.ts","timestamp":1727452331795},{"id":"NiEX.ts","timestamp":1727452357953},{"id":"vl2v.ts","timestamp":1727452371114},{"id":"9k5B.ts","source":"Fix all fixable ESLint issues","timestamp":1727452390189},{"id":"LA6K.ts","source":"Fix all fixable ESLint issues","timestamp":1727452515233},{"id":"DQRM.ts","timestamp":1727452548341},{"id":"N0vw.ts","source":"Fix all fixable ESLint issues","timestamp":1727452563235},{"id":"wovo.ts","timestamp":1727452589497},{"id":"pDg4.ts","timestamp":1727452608441},{"id":"CMIH.ts","timestamp":1727452618502},{"id":"GuCw.ts","timestamp":1727452652489},{"id":"IcIs.ts","timestamp":1727452683642},{"id":"n4lh.ts","timestamp":1727452763636},{"id":"HsE5.ts","source":"Fix all fixable ESLint issues","timestamp":1727452808482},{"id":"kAX5.ts","timestamp":1727452830342},{"id":"Q1L3.ts","timestamp":1727452890049},{"id":"2cBI.ts","source":"Fix all fixable ESLint issues","timestamp":1727452992973},{"id":"bL1o.ts","timestamp":1727453002632},{"id":"edma.ts","timestamp":1727453039628},{"id":"eob3.ts","source":"Fix all fixable ESLint issues","timestamp":1727453052870},{"id":"WiGM.ts","timestamp":1727453074980},{"id":"LHW0.ts","timestamp":1727774514980},{"id":"NZ8D.ts","timestamp":1727774525417},{"id":"kBnW.ts","timestamp":1727774563246},{"id":"QYl7.ts","timestamp":1727774581543},{"id":"KHEs.ts","source":"Fix all fixable ESLint issues","timestamp":1727774637298},{"id":"edhB.ts","source":"Fix all fixable ESLint issues","timestamp":1727774674027},{"id":"tXuy.ts","timestamp":1727774686601},{"id":"UQAZ.ts","timestamp":1727774747799},{"id":"ooPa.ts","timestamp":1727774759524},{"id":"jgzm.ts","timestamp":1727774781870},{"id":"x3J8.ts","source":"Fix all fixable ESLint issues","timestamp":1727774789054},{"id":"8cFP.ts","source":"Fix all fixable ESLint issues","timestamp":1727774840232}]}